{"RBVUHOYLsII3jEzTVsdM1Q==":"lunda-1200x803.jpg","2G46d2pfHTY0mc4qZpYyXg==":"mbr-810x1080.jpg","GsRzQyK3CLg0iBNdSirZrA==":"logoluna-275x128.png","PFAw1AnybB8djBrgRIRnBQ==":"logolunasi-381x128.png","X+j9aCKqlP5wj+AJE0OZ2Q==":"logolunavec.svg","IFgvFO46wrft0f7ROhsvUw==":"logolunavec-1.svg","PR02HmtT3Kx55XJhyV0w7g==":"cejar1-720x720.jpg","2Rm3uSWSHLFDhAc4ae90WA==":"piedras%20rojas1-615x615.jpg","kt57dbCCN66TzuXV40XtCw==":"cejar1-1-720x720.jpg","+RK709ChMOHoP/qqpqSsOg==":"geyser-720x720.jpg","77NYRwocoI87lNEHfgufJA==":"escondidas-720x405.jpg","kEReens8Fm2J+b5XiX+2Ng==":"escondidassi-1024x830.jpg","C9WvS4pheKb6aLFxMb+Ggg==":"piedras%20rojas1-615x615.jpg","B8+sQI7eZUORVWv8fimAiw==":"taratara-1400x927.jpg","pAix+0EvT1KRMQ3icS/a4w==":"puritama-720x720.jpg","uQ2jenPc9N4EXWM6JHOyNg==":"astronomico1-720x982.jpg","rQT/EXuiZTa9uWMvheci6A==":"luna%20luna%20si-550x413.jpg","ZkEvMW8fA2XRltX3I6E4cg==":"lunanevemk-1024x621.jpg","h2BbBTVhXXuuoz+9GVsS3w==":"arcoiris-550x367.jpg","6NwTc9+i31jTD6LNvyxwuw==":"uyuni-720x540.jpg","lSvD6O5lXW1uOave8obDmA==":"geyser-1-720x720.jpg","TYpO+I145xabphirWYbZMw==":"2geyser-2000x1334.jpg","xuoeKmC5R30sLvzlPqyHmw==":"2geyser-2000x1333.jpg","8GhuXwCE2G7RFWq20oKBoA==":"2lagunas-1600x1063.jpg","SRypNGq4jiH+CzzsUU/LFQ==":"2luna-1440x760.jpg","pWaUNdJf3cfcqstKx7BS4A==":"2piedras-1224x918.jpg","ZxkMENBEjZ7I3q47qXhf4A==":"2piedras-1100x760.jpg","VdtEm/4OKsV0lvy8mDMpKg==":"2cejar-1280x720.jpg","dv0jHc93uwjtBRkbo90ieg==":"2tara-1100x733.jpg","sgeZji3+UpylQLHkWxsvGw==":"2puritama-2000x1500.jpg","Jxg1OzuQSlJ4RtDXRokG3w==":"2astronomico-1440x981.jpg","XlmIM84I+t2+W95UI5nsfg==":"2arcoiris-1024x768.jpg","WINrWImGG9d+UXcU+fQo9g==":"2uyuni-1250x834.jpg"}